{"@context":"https://iiif.io/api/presentation/3/context.json","id":"https://markpbaggett.github.io/rfta_winter_2023/api/facet/subject/prayer.json","type":"Collection","label":{"none":["Prayer"]},"items":[{"id":"https://digital.lib.utk.edu/assemble/manifest/rftaart/77","type":"Manifest","label":{"en":["Bob Sweeney Prays"]},"thumbnail":[{"id":"https://digital.lib.utk.edu/collections/islandora/object/rftaart%3A77/datastream/TN","width":200,"height":200,"type":"Image","format":"image/jpeg"}],"homepage":[{"id":"https://markpbaggett.github.io/rfta_winter_2023/works/bob-sweeney-prays","type":"Text","label":{"en":["Bob Sweeney Prays"]}}]}],"partOf":[{"id":"https://markpbaggett.github.io/rfta_winter_2023/api/facet/subject.json","type":"Collection"}],"summary":{"none":["Subject"]},"homepage":[{"id":"https://markpbaggett.github.io/rfta_winter_2023/search?subject=prayer","type":"Text","label":{"none":["Prayer"]}}]}